[
    {
        "pool": "GOMA",
        "weight raw": 25472.46,
        "cashg's": 11561,
        "cg matched": 7814,
        "cg matched%": 67.58930888331459,
        "gnomeskies": 9,
        "gn matched": 0,
        "gn matched%": 0.0,
        "special gnomes": 1,
        "shittis with cgs": 8634,
        "shittis": 6
    },
    {
        "pool": "HAWAK",
        "weight raw": 24001.6,
        "cashg's": 9808,
        "cg matched": 7448,
        "cg matched%": 75.93800978792822,
        "gnomeskies": 45,
        "gn matched": 0,
        "gn matched%": 0.0,
        "special gnomes": 8,
        "shittis with cgs": 8740,
        "shittis": 7
    },
    {
        "pool": "RARE",
        "weight raw": 19956.73,
        "cashg's": 10842,
        "cg matched": 3420,
        "cg matched%": 31.54399557277255,
        "gnomeskies": 43,
        "gn matched": 0,
        "gn matched%": 0.0,
        "special gnomes": 14,
        "shittis with cgs": 7217,
        "shittis": 4
    },
    {
        "pool": "SALT",
        "weight raw": 22481.9,
        "cashg's": 10805,
        "cg matched": 7086,
        "cg matched%": 65.58074965293845,
        "gnomeskies": 28,
        "gn matched": 17,
        "gn matched%": 60.71428571428571,
        "special gnomes": 9,
        "shittis with cgs": 5610,
        "shittis": 1
    },
    {
        "pool": "CHEF",
        "weight raw": 23853.53,
        "cashg's": 12609,
        "cg matched": 4327,
        "cg matched%": 34.31675787136172,
        "gnomeskies": 58,
        "gn matched": 42,
        "gn matched%": 72.41379310344827,
        "special gnomes": 2,
        "shittis with cgs": 7837,
        "shittis": 3
    },
    {
        "pool": "QCPOL",
        "weight raw": 26888.98,
        "cashg's": 13332,
        "cg matched": 7782,
        "cg matched%": 58.37083708370837,
        "gnomeskies": 56,
        "gn matched": 30,
        "gn matched%": 53.57142857142857,
        "special gnomes": 8,
        "shittis with cgs": 6442,
        "shittis": 4
    },
    {
        "pool": "ITZA",
        "weight raw": 23661.91,
        "cashg's": 12242,
        "cg matched": 4627,
        "cg matched%": 37.796111746446655,
        "gnomeskies": 120,
        "gn matched": 94,
        "gn matched%": 78.33333333333333,
        "special gnomes": 35,
        "shittis with cgs": 4939,
        "shittis": 3
    },
    {
        "pool": "SEA",
        "weight raw": 25690.54,
        "cashg's": 14882,
        "cg matched": 4353,
        "cg matched%": 29.25010079290418,
        "gnomeskies": 187,
        "gn matched": 119,
        "gn matched%": 63.63636363636363,
        "special gnomes": 19,
        "shittis with cgs": 2566,
        "shittis": 3
    },
    {
        "pool": "WOOF",
        "weight raw": 21515.62,
        "cashg's": 11542,
        "cg matched": 4829,
        "cg matched%": 41.8385028591232,
        "gnomeskies": 88,
        "gn matched": 71,
        "gn matched%": 80.68181818181817,
        "special gnomes": 14,
        "shittis with cgs": 3898,
        "shittis": 4
    },
    {
        "pool": "DDOS",
        "weight raw": 24382.53,
        "cashg's": 10376,
        "cg matched": 6116,
        "cg matched%": 58.94371626831148,
        "gnomeskies": 147,
        "gn matched": 117,
        "gn matched%": 79.59183673469387,
        "special gnomes": 22,
        "shittis with cgs": 5537,
        "shittis": 3
    },
    {
        "pool": "FARM",
        "weight raw": 46724.07,
        "cashg's": 25451,
        "cg matched": 6885,
        "cg matched%": 27.05198224038348,
        "gnomeskies": 112,
        "gn matched": 43,
        "gn matched%": 38.392857142857146,
        "special gnomes": 11,
        "shittis with cgs": 17403,
        "shittis": 13
    },
    {
        "pool": "PSYA",
        "weight raw": 23148.0,
        "cashg's": 14040,
        "cg matched": 3227,
        "cg matched%": 22.984330484330485,
        "gnomeskies": 155,
        "gn matched": 101,
        "gn matched%": 65.16129032258064,
        "special gnomes": 8,
        "shittis with cgs": 2900,
        "shittis": 2
    },
    {
        "pool": "PSB",
        "weight raw": 25060.61,
        "cashg's": 11573,
        "cg matched": 5583,
        "cg matched%": 48.24159682018491,
        "gnomeskies": 69,
        "gn matched": 47,
        "gn matched%": 68.11594202898551,
        "special gnomes": 9,
        "shittis with cgs": 8869,
        "shittis": 7
    },
    {
        "pool": "A3C",
        "weight raw": 22151.21,
        "cashg's": 13421,
        "cg matched": 3866,
        "cg matched%": 28.805603159228077,
        "gnomeskies": 77,
        "gn matched": 46,
        "gn matched%": 59.74025974025974,
        "special gnomes": 23,
        "shittis with cgs": 4209,
        "shittis": 4
    },
    {
        "pool": "BONE",
        "weight raw": 28476.23,
        "cashg's": 15411,
        "cg matched": 5567,
        "cg matched%": 36.1235481149828,
        "gnomeskies": 114,
        "gn matched": 88,
        "gn matched%": 77.19298245614034,
        "special gnomes": 15,
        "shittis with cgs": 6367,
        "shittis": 4
    },
    {
        "pool": "PRIDE",
        "weight raw": 23176.9,
        "cashg's": 14883,
        "cg matched": 4197,
        "cg matched%": 28.19995968554727,
        "gnomeskies": 100,
        "gn matched": 53,
        "gn matched%": 53.0,
        "special gnomes": 14,
        "shittis with cgs": 2510,
        "shittis": 3
    },
    {
        "pool": "VEGAS",
        "weight raw": 28690.37,
        "cashg's": 17049,
        "cg matched": 5166,
        "cg matched%": 30.300897413338024,
        "gnomeskies": 197,
        "gn matched": 105,
        "gn matched%": 53.299492385786806,
        "special gnomes": 34,
        "shittis with cgs": 2573,
        "shittis": 3
    },
    {
        "pool": "HAZEL",
        "weight raw": 31660.5,
        "cashg's": 15587,
        "cg matched": 6657,
        "cg matched%": 42.70866747930968,
        "gnomeskies": 48,
        "gn matched": 33,
        "gn matched%": 68.75,
        "special gnomes": 5,
        "shittis with cgs": 11850,
        "shittis": 4
    },
    {
        "pool": "BAIDU",
        "weight raw": 23518.57,
        "cashg's": 11888,
        "cg matched": 4659,
        "cg matched%": 39.190780619111706,
        "gnomeskies": 91,
        "gn matched": 69,
        "gn matched%": 75.82417582417582,
        "special gnomes": 10,
        "shittis with cgs": 6553,
        "shittis": 5
    },
    {
        "pool": "LIDO",
        "weight raw": 22562.07,
        "cashg's": 11563,
        "cg matched": 5923,
        "cg matched%": 51.223730865692296,
        "gnomeskies": 92,
        "gn matched": 76,
        "gn matched%": 82.6086956521739,
        "special gnomes": 14,
        "shittis with cgs": 3603,
        "shittis": 5
    },
    {
        "pool": "ASPEN",
        "weight raw": 24012.67,
        "cashg's": 12616,
        "cg matched": 5888,
        "cg matched%": 46.6708941027267,
        "gnomeskies": 14,
        "gn matched": 0,
        "gn matched%": 0.0,
        "special gnomes": 5,
        "shittis with cgs": 7643,
        "shittis": 4
    },
    {
        "pool": "STOIC",
        "weight raw": 22625.72,
        "cashg's": 10492,
        "cg matched": 7706,
        "cg matched%": 73.44643537933663,
        "gnomeskies": 23,
        "gn matched": 0,
        "gn matched%": 0.0,
        "special gnomes": 4,
        "shittis with cgs": 5888,
        "shittis": 3
    }
]