[
    {
        "pool": "GOMA",
        "weight raw": 26936.5,
        "cashg's": 11998,
        "cg matched": 8499,
        "cg matched%": 70.83680613435573,
        "gnomeskies": 12,
        "gn matched": 0,
        "gn matched%": 0.0,
        "special gnomes": 3,
        "shittis with cgs": 9050,
        "shittis": 5
    },
    {
        "pool": "HAWAK",
        "weight raw": 22648.9,
        "cashg's": 9278,
        "cg matched": 7663,
        "cg matched%": 82.5932312998491,
        "gnomeskies": 14,
        "gn matched": 0,
        "gn matched%": 0.0,
        "special gnomes": 8,
        "shittis with cgs": 7910,
        "shittis": 6
    },
    {
        "pool": "RARE",
        "weight raw": 24569.58,
        "cashg's": 12566,
        "cg matched": 5199,
        "cg matched%": 41.37354766831132,
        "gnomeskies": 45,
        "gn matched": 0,
        "gn matched%": 0.0,
        "special gnomes": 14,
        "shittis with cgs": 8782,
        "shittis": 5
    },
    {
        "pool": "SALT",
        "weight raw": 26732.29,
        "cashg's": 12782,
        "cg matched": 8315,
        "cg matched%": 65.05241746205601,
        "gnomeskies": 56,
        "gn matched": 25,
        "gn matched%": 44.642857142857146,
        "special gnomes": 9,
        "shittis with cgs": 6341,
        "shittis": 1
    },
    {
        "pool": "CHEF",
        "weight raw": 27386.25,
        "cashg's": 13852,
        "cg matched": 5748,
        "cg matched%": 41.49581287900664,
        "gnomeskies": 59,
        "gn matched": 40,
        "gn matched%": 67.79661016949152,
        "special gnomes": 1,
        "shittis with cgs": 9125,
        "shittis": 5
    },
    {
        "pool": "QCPOL",
        "weight raw": 27970.05,
        "cashg's": 13755,
        "cg matched": 8117,
        "cg matched%": 59.01126862958924,
        "gnomeskies": 57,
        "gn matched": 32,
        "gn matched%": 56.14035087719298,
        "special gnomes": 8,
        "shittis with cgs": 6845,
        "shittis": 4
    },
    {
        "pool": "ITZA",
        "weight raw": 26342.989999999998,
        "cashg's": 13487,
        "cg matched": 5650,
        "cg matched%": 41.89219248164899,
        "gnomeskies": 138,
        "gn matched": 114,
        "gn matched%": 82.6086956521739,
        "special gnomes": 13,
        "shittis with cgs": 4871,
        "shittis": 3
    },
    {
        "pool": "SEA",
        "weight raw": 26576.79,
        "cashg's": 15506,
        "cg matched": 4828,
        "cg matched%": 31.136334322197857,
        "gnomeskies": 180,
        "gn matched": 110,
        "gn matched%": 61.111111111111114,
        "special gnomes": 21,
        "shittis with cgs": 2591,
        "shittis": 3
    },
    {
        "pool": "WOOF",
        "weight raw": 24469.68,
        "cashg's": 13085,
        "cg matched": 6229,
        "cg matched%": 47.604126862820024,
        "gnomeskies": 102,
        "gn matched": 77,
        "gn matched%": 75.49019607843137,
        "special gnomes": 15,
        "shittis with cgs": 3472,
        "shittis": 4
    },
    {
        "pool": "DDOS",
        "weight raw": 26346.02,
        "cashg's": 10983,
        "cg matched": 6540,
        "cg matched%": 59.546571974870254,
        "gnomeskies": 178,
        "gn matched": 138,
        "gn matched%": 77.52808988764045,
        "special gnomes": 22,
        "shittis with cgs": 5758,
        "shittis": 3
    },
    {
        "pool": "FARM",
        "weight raw": 36888.36,
        "cashg's": 19928,
        "cg matched": 5787,
        "cg matched%": 29.03954235246889,
        "gnomeskies": 77,
        "gn matched": 31,
        "gn matched%": 40.25974025974026,
        "special gnomes": 14,
        "shittis with cgs": 13744,
        "shittis": 12
    },
    {
        "pool": "PSYA",
        "weight raw": 28635.28,
        "cashg's": 16140,
        "cg matched": 4125,
        "cg matched%": 25.55762081784387,
        "gnomeskies": 130,
        "gn matched": 89,
        "gn matched%": 68.46153846153847,
        "special gnomes": 8,
        "shittis with cgs": 7312,
        "shittis": 3
    },
    {
        "pool": "PSB",
        "weight raw": 26420.96,
        "cashg's": 12047,
        "cg matched": 6168,
        "cg matched%": 51.199468747405994,
        "gnomeskies": 69,
        "gn matched": 48,
        "gn matched%": 69.56521739130434,
        "special gnomes": 9,
        "shittis with cgs": 9284,
        "shittis": 7
    },
    {
        "pool": "A3C",
        "weight raw": 27129.28,
        "cashg's": 15141,
        "cg matched": 5659,
        "cg matched%": 37.375338484908525,
        "gnomeskies": 126,
        "gn matched": 77,
        "gn matched%": 61.111111111111114,
        "special gnomes": 48,
        "shittis with cgs": 4412,
        "shittis": 5
    },
    {
        "pool": "BONE",
        "weight raw": 27299.25,
        "cashg's": 14105,
        "cg matched": 5356,
        "cg matched%": 37.97235023041475,
        "gnomeskies": 124,
        "gn matched": 98,
        "gn matched%": 79.03225806451613,
        "special gnomes": 15,
        "shittis with cgs": 6425,
        "shittis": 4
    },
    {
        "pool": "PRIDE",
        "weight raw": 22610.5,
        "cashg's": 13962,
        "cg matched": 4790,
        "cg matched%": 34.3074058157857,
        "gnomeskies": 101,
        "gn matched": 53,
        "gn matched%": 52.475247524752476,
        "special gnomes": 13,
        "shittis with cgs": 2150,
        "shittis": 3
    },
    {
        "pool": "VEGAS",
        "weight raw": 28201.36,
        "cashg's": 17202,
        "cg matched": 5335,
        "cg matched%": 31.01383560051157,
        "gnomeskies": 161,
        "gn matched": 84,
        "gn matched%": 52.17391304347826,
        "special gnomes": 33,
        "shittis with cgs": 2644,
        "shittis": 3
    },
    {
        "pool": "HAZEL",
        "weight raw": 27072.059999999998,
        "cashg's": 13578,
        "cg matched": 5597,
        "cg matched%": 41.22109294446899,
        "gnomeskies": 52,
        "gn matched": 37,
        "gn matched%": 71.15384615384616,
        "special gnomes": 5,
        "shittis with cgs": 9474,
        "shittis": 2
    },
    {
        "pool": "BAIDU",
        "weight raw": 23609.62,
        "cashg's": 11143,
        "cg matched": 5604,
        "cg matched%": 50.29166292739836,
        "gnomeskies": 98,
        "gn matched": 76,
        "gn matched%": 77.55102040816327,
        "special gnomes": 9,
        "shittis with cgs": 6098,
        "shittis": 5
    },
    {
        "pool": "LIDO",
        "weight raw": 23070.41,
        "cashg's": 11943,
        "cg matched": 6656,
        "cg matched%": 55.73139077283764,
        "gnomeskies": 68,
        "gn matched": 60,
        "gn matched%": 88.23529411764706,
        "special gnomes": 15,
        "shittis with cgs": 3589,
        "shittis": 5
    },
    {
        "pool": "ASPEN",
        "weight raw": 24277.489999999998,
        "cashg's": 12262,
        "cg matched": 6185,
        "cg matched%": 50.440384929049095,
        "gnomeskies": 23,
        "gn matched": 0,
        "gn matched%": 0.0,
        "special gnomes": 4,
        "shittis with cgs": 7921,
        "shittis": 4
    },
    {
        "pool": "STOIC",
        "weight raw": 28048.489999999998,
        "cashg's": 12886,
        "cg matched": 9026,
        "cg matched%": 70.0450100884681,
        "gnomeskies": 25,
        "gn matched": 0,
        "gn matched%": 0.0,
        "special gnomes": 4,
        "shittis with cgs": 8321,
        "shittis": 4
    }
]